async_repool/__init__.py
async_repool/async_pool.py
tests/__init__.py
tests/test_pool.py
async_repool-1.0.1.dist-info/LICENSE.txt
async_repool-1.0.1.dist-info/METADATA
async_repool-1.0.1.dist-info/WHEEL
async_repool-1.0.1.dist-info/top_level.txt
async_repool-1.0.1.dist-info/RECORD
