Metadata-Version: 2.1
Name: async-repool
Version: 1.0.1
Summary: AsyncIO connection pool for RethinkDB
Home-page: https://gitlab.com/AnjiProject/async-repool
Author: Bogdan Gladyshev
Author-email: siredvin.dark@gmail.com
License: MIT license
Keywords: rethinkdb asyncio connection pool
Platform: UNKNOWN
Classifier: Development Status :: 5 - Production/Stable
Classifier: Intended Audience :: Developers
Classifier: License :: OSI Approved :: MIT License
Classifier: Natural Language :: English
Classifier: Programming Language :: Python :: 3.5
Classifier: Programming Language :: Python :: 3.6
Classifier: Framework :: AsyncIO
Requires-Dist: rethinkdb (>=2.4.0)
Requires-Dist: tenacity (>=5.0.0)
